nIRC/__init__.py
nIRC/irc.py
nirc-1.0.2.dist-info/licenses/LICENSE
nirc-1.0.2.dist-info/METADATA
nirc-1.0.2.dist-info/WHEEL
nirc-1.0.2.dist-info/top_level.txt
nirc-1.0.2.dist-info/RECORD
