Metadata-Version: 2.4
Name: nIRC
Version: 1.0.2
Summary: an asynchronous IRC bot framework
Author-email: NekoMimiOfficial <nekomimi@tilde.team>
Keywords: irc,python,library,asynchronous
Classifier: Programming Language :: Python :: 3
Classifier: License :: OSI Approved :: MIT License
Classifier: Operating System :: OS Independent
Classifier: Topic :: Utilities
Requires-Python: >=3.8
License-File: LICENSE
Dynamic: license-file
